Workbook

Sheet App
B20: Informações Iniciais
B21: Salário | D21: 5000
B22: Perfil de investidor | D22: Moderado
B23: Sugestão de investimento (% da renda) | D23: 0.3
B24: Rendimento da Carteira (% aproximada) | D24: =VLOOKUP(D22,Carteiras!G2:I5,2,FALSE) -> 1,0% – 1,2%
B25: Risco | D25: =VLOOKUP(D22,Carteiras!G2:I5,3,FALSE) -> Médio
B27: Investimento Mensal
B28: Quanto investir por mês? | D28: 1000
A29: 12 | B29: Por quantos anos? | D29: 10
B30: Taxa de rendimento mensal | D30: 0.01
B31: Patrimônio acumulado | D31: =FV(D30,D29*A29,D28)*-1 -> 230038.69
B32: Dividendos mensais | D32: =D31*D30 -> 2300.3869
B34: Cenários
B35: Período | C35: Patrimônio Acumulado | D35: Dividendos
A36: 2 | B36: Em 2 anos | C36: =FV($D$30,A36*$A$29,$D$28)*-1 -> 26973.465 | D36: =C36*$D$30 -> 269.73465
A37: 5 | B37: Em 5 anos | C37: =FV($D$30,A37*$A$29,$D$28)*-1 -> 81669.67 | D37: =C37*$D$30 -> 816.6967
A38: 10 | B38: Em 10 anos | C38: =FV($D$30,A38*$A$29,$D$28)*-1 -> 230038.69 | D38: =C38*$D$30 -> 2300.3869
A39: 20 | B39: Em 20 anos | C39: =FV($D$30,A39*$A$29,$D$28)*-1 -> 989255.37 | D39: =C39*$D$30 -> 9892.5537
A40: 30 | B40: Em 30 anos | C40: =FV($D$30,A40*$A$29,$D$28)*-1 -> 3494964.1 | D40: =C40*$D$30 -> 34949.641
B42: Perfil: | D42: =D22 -> Moderado
B43: Valor a ser investido por mês: | D43: 1000
B45: Carteira
B46: Tipo de FII | C46: % Sugerido | D46: Valor
B47: Tijolo | C47: =VLOOKUP($D$42&" - "&B47,Carteiras!B2:E20,4,FALSE) -> 0.4 | D47: =$D$43*C47 -> 400
B48: Papel | C48: =VLOOKUP($D$42&" - "&B48,Carteiras!B3:E21,4,FALSE) -> 0.2 | D48: =$D$43*C48 -> 200
B49: Híbridos | C49: =VLOOKUP($D$42&" - "&B49,Carteiras!B4:E22,4,FALSE) -> 0.15 | D49: =$D$43*C49 -> 150
B50: Fundos de Fundos (FoFs) | C50: =VLOOKUP($D$42&" - "&B50,Carteiras!B5:E23,4,FALSE) -> 0.15 | D50: =$D$43*C50 -> 150
B51: Desenvolvimento | C51: =VLOOKUP($D$42&" - "&B51,Carteiras!B6:E24,4,FALSE) -> 0.05 | D51: =$D$43*C51 -> 50
B52: Fiagros | C52: =VLOOKUP($D$42&" - "&B52,Carteiras!B7:E25,4,FALSE) -> 0.05 | D52: =$D$43*C52 -> 50
B53: TOTAL | C53: =SUM(C47:C52) -> 1 | D53: =SUM(D47:D52) -> 1000
D74: Elaborado por: Leandro Almeida

Sheet Carteiras
B2: Chave | C2: Perfil | D2: Tipo FII | E2: % | G2: Perfil | H2: Rendimento | I2: Risco
B3: =C3&" - "&D3 -> Conservador - Tijolo | C3: Conservador | D3: Tijolo | E3: 0.6 | G3: Conservador | H3: 0,8% – 1,0% | I3: Baixo
B4: =C4&" - "&D4 -> Conservador - Papel | C4: Conservador | D4: Papel | E4: 0.25 | G4: Moderado | H4: 1,0% – 1,2% | I4: Médio
B5: =C5&" - "&D5 -> Conservador - Híbridos | C5: Conservador | D5: Híbridos | E5: 0.15 | G5: Arrojado | H5: 1,2% – 1,8% | I5: Alto
B6: =C6&" - "&D6 -> Conservador - Fundos de Fundos (FoFs) | C6: Conservador | D6: Fundos de Fundos (FoFs) | E6: 0
B7: =C7&" - "&D7 -> Conservador - Desenvolvimento | C7: Conservador | D7: Desenvolvimento | E7: 0
B8: =C8&" - "&D8 -> Conservador - Fiagros | C8: Conservador | D8: Fiagros | E8: 0
B9: =C9&" - "&D9 -> Moderado - Tijolo | C9: Moderado | D9: Tijolo | E9: 0.4
B10: =C10&" - "&D10 -> Moderado - Papel | C10: Moderado | D10: Papel | E10: 0.2
B11: =C11&" - "&D11 -> Moderado - Híbridos | C11: Moderado | D11: Híbridos | E11: 0.15
B12: =C12&" - "&D12 -> Moderado - Fundos de Fundos (FoFs) | C12: Moderado | D12: Fundos de Fundos (FoFs) | E12: 0.15
B13: =C13&" - "&D13 -> Moderado - Desenvolvimento | C13: Moderado | D13: Desenvolvimento | E13: 0.05
B14: =C14&" - "&D14 -> Moderado - Fiagros | C14: Moderado | D14: Fiagros | E14: 0.05
B15: =C15&" - "&D15 -> Arrojado - Tijolo | C15: Arrojado | D15: Tijolo | E15: 0.2
B16: =C16&" - "&D16 -> Arrojado - Papel | C16: Arrojado | D16: Papel | E16: 0.25
B17: =C17&" - "&D17 -> Arrojado - Híbridos | C17: Arrojado | D17: Híbridos | E17: 0.2
... B20: =C20&" - "&D20 -> Arrojado - Fiagros | C20: Arrojado | D20: Fiagros | E20: 0.1
